Metadata-Version: 2.4
Name: plutoxyz-browser-use
Version: 0.5.0
Summary: Make websites accessible for AI agents
Project-URL: Repository, https://github.com/browser-use/browser-use
Author: Gregor Zunic
License-File: LICENSE
Classifier: License :: OSI Approved :: MIT License
Classifier: Operating System :: OS Independent
Classifier: Programming Language :: Python :: 3
Requires-Python: <4.0,>=3.11
Requires-Dist: aiofiles>=24.1.0
Requires-Dist: anthropic>=0.54.0
Requires-Dist: anyio>=4.9.0
Requires-Dist: authlib>=1.6.0
Requires-Dist: bubus>=1.4.1
Requires-Dist: google-api-core>=2.25.0
Requires-Dist: google-api-python-client>=2.174.0
Requires-Dist: google-auth-oauthlib>=1.2.2
Requires-Dist: google-auth>=2.40.3
Requires-Dist: google-genai>=1.21.1
Requires-Dist: groq>=0.28.0
Requires-Dist: httpx>=0.28.1
Requires-Dist: markdownify==1.1.0
Requires-Dist: mcp>=1.10.1
Requires-Dist: ollama>=0.5.1
Requires-Dist: openai>=1.81.0
Requires-Dist: patchright>=1.52.5
Requires-Dist: playwright>=1.52.0
Requires-Dist: portalocker<3.0.0,>=2.7.0
Requires-Dist: posthog>=3.7.0
Requires-Dist: psutil>=7.0.0
Requires-Dist: pydantic>=2.11.5
Requires-Dist: pyobjc>=11.0; platform_system == 'darwin'
Requires-Dist: pypdf>=5.7.0
Requires-Dist: pyperclip>=1.9.0
Requires-Dist: python-dotenv>=1.0.1
Requires-Dist: requests>=2.32.3
Requires-Dist: screeninfo>=0.8.1; platform_system != 'darwin'
Requires-Dist: typing-extensions>=4.12.2
Requires-Dist: uuid7>=0.1.0
Provides-Extra: all
Requires-Dist: browser-use[aws,cli,examples]; extra == 'all'
Provides-Extra: aws
Requires-Dist: boto3>=1.38.45; extra == 'aws'
Provides-Extra: cli
Requires-Dist: click>=8.1.8; extra == 'cli'
Requires-Dist: rich>=14.0.0; extra == 'cli'
Requires-Dist: textual>=3.2.0; extra == 'cli'
Provides-Extra: eval
Requires-Dist: anyio>=4.9.0; extra == 'eval'
Requires-Dist: browserbase==1.4.0; extra == 'eval'
Requires-Dist: datamodel-code-generator>=0.26.0; extra == 'eval'
Requires-Dist: hyperbrowser==0.47.0; extra == 'eval'
Requires-Dist: lmnr[all]>=0.6.11; extra == 'eval'
Requires-Dist: pillow>=11.2.1; extra == 'eval'
Requires-Dist: psutil>=7.0.0; extra == 'eval'
Provides-Extra: examples
Requires-Dist: botocore>=1.37.23; extra == 'examples'
Requires-Dist: browserbase>=0.4.0; extra == 'examples'
Requires-Dist: imgcat>=0.6.0; extra == 'examples'
Requires-Dist: langchain-openai>=0.3.26; extra == 'examples'
Requires-Dist: stagehand-py>=0.3.6; extra == 'examples'
